predictnow/__init__.py
predictnow/find_files_with_specific_extensions.py
predictnow/pdapi.py
predictnow/predict_result.py
predictnow/training_result.py
predictnow-2.1.4.dist-info/LICENSE
predictnow-2.1.4.dist-info/METADATA
predictnow-2.1.4.dist-info/WHEEL
predictnow-2.1.4.dist-info/RECORD
