Metadata-Version: 2.1
Name: predictnow
Version: 2.1.4
Summary: A restful client library, designed to access predictnow restful API.
License: MIT
Author: PredictNow
Author-email: tech@predictnow.ai
Requires-Python: >=3.10,<4.0
Classifier: License :: OSI Approved :: MIT License
Classifier: Programming Language :: Python :: 3
Classifier: Programming Language :: Python :: 3.10
Classifier: Programming Language :: Python :: 3.11
Requires-Dist: pandas (>=2.2.3,<3.0.0)
Requires-Dist: pyarrow (>=17.0.0,<18.0.0)
Requires-Dist: requests (>=2.32.3,<3.0.0)
